{
  "baselineId": "A",
  "baselineName": "empty",
  "seed": 99,
  "epochs": [
    {
      "epoch": 1,
      "accepted": true,
      "errorCode": null,
      "beforeComposite": 0,
      "afterComposite": 0.023529411764705882,
      "marginalDelta": 0.023529411764705882,
      "latencyMs": 134.519834,
      "components": {
        "exactRetrieval": 0,
        "staleMemoryRejection": 0,
        "temporalUpdateCorrectness": 0,
        "compressionSurvival": 0.0784313725490196,
        "routingAccuracy": 0,
        "latencyMs": 0
      },
      "parentStateRoot": "0x545a95d0e6b645f21c36b18afa36e52c5c8a15923b91f06fdbdea258596dd04f",
      "patchHashHex": "0xca6b1f7a58052a8a4f217d0398c6b6d294ba6f377b28bbe02e3e8be0ef751522"
    },
    {
      "epoch": 2,
      "accepted": true,
      "errorCode": null,
      "beforeComposite": 0.023529411764705882,
      "afterComposite": 0.047058823529411764,
      "marginalDelta": 0.023529411764705882,
      "latencyMs": 131.951941,
      "components": {
        "exactRetrieval": 0,
        "staleMemoryRejection": 0,
        "temporalUpdateCorrectness": 0,
        "compressionSurvival": 0.1568627450980392,
        "routingAccuracy": 0,
        "latencyMs": 0
      },
      "parentStateRoot": "0x92f3fb48a9682fa61f7aaa43076e88d73ee326b6560a2045dc534b1e37344425",
      "patchHashHex": "0xb3f32f6896751322d50113c7285d45de299177f4e88f224449ba1416dfac4b6c"
    },
    {
      "epoch": 3,
      "accepted": true,
      "errorCode": null,
      "beforeComposite": 0.047058823529411764,
      "afterComposite": 0.07058823529411765,
      "marginalDelta": 0.023529411764705882,
      "latencyMs": 133.213417,
      "components": {
        "exactRetrieval": 0,
        "staleMemoryRejection": 0,
        "temporalUpdateCorrectness": 0,
        "compressionSurvival": 0.23529411764705882,
        "routingAccuracy": 0,
        "latencyMs": 0
      },
      "parentStateRoot": "0xde436f0908305572c15f11bd5b078ce5bca05dc18b0d52ad9f4e4cc264769745",
      "patchHashHex": "0xfb7c39d16f40cf921d2c6defb5b1195f2fa34654665e81264b0a7d1966aefa2a"
    },
    {
      "epoch": 4,
      "accepted": true,
      "errorCode": null,
      "beforeComposite": 0.07058823529411765,
      "afterComposite": 0.09411764705882353,
      "marginalDelta": 0.023529411764705882,
      "latencyMs": 134.08884,
      "components": {
        "exactRetrieval": 0,
        "staleMemoryRejection": 0,
        "temporalUpdateCorrectness": 0,
        "compressionSurvival": 0.3137254901960784,
        "routingAccuracy": 0,
        "latencyMs": 0
      },
      "parentStateRoot": "0x969081f9a4fed3e73a7feb016bc6ab48b413fc9bd9b9e6db9d7c02c1206ec7bf",
      "patchHashHex": "0x73a63ce23c1654563d924d906b061d9defac82ed7ac2d0993710e2ed68e0b2e5"
    },
    {
      "epoch": 5,
      "accepted": true,
      "errorCode": null,
      "beforeComposite": 0.09411764705882353,
      "afterComposite": 0.11764705882352941,
      "marginalDelta": 0.023529411764705882,
      "latencyMs": 138.623849,
      "components": {
        "exactRetrieval": 0,
        "staleMemoryRejection": 0,
        "temporalUpdateCorrectness": 0,
        "compressionSurvival": 0.39215686274509803,
        "routingAccuracy": 0,
        "latencyMs": 0
      },
      "parentStateRoot": "0x8594a7636bcc05c63fa0a2ba9c1ed2990364e522cbf5eefed4548d19ef8113c9",
      "patchHashHex": "0xe29b6216ce1fcf38f9c1c6bdd6a91faf236e315104af0a14e06015933eb25bd4"
    },
    {
      "epoch": 6,
      "accepted": true,
      "errorCode": null,
      "beforeComposite": 0.11764705882352941,
      "afterComposite": 0.1411764705882353,
      "marginalDelta": 0.023529411764705882,
      "latencyMs": 140.453076,
      "components": {
        "exactRetrieval": 0,
        "staleMemoryRejection": 0,
        "temporalUpdateCorrectness": 0,
        "compressionSurvival": 0.47058823529411764,
        "routingAccuracy": 0,
        "latencyMs": 0
      },
      "parentStateRoot": "0x08364db6c69313dfc06ac6f1d187ff613650f351ef7501b864f0d6b91a794d4d",
      "patchHashHex": "0xe64ba6c0fa1f2153ba916e11cf4f4ae3ac3f8c07d56973ccb1ae47336a92b0b1"
    },
    {
      "epoch": 7,
      "accepted": true,
      "errorCode": null,
      "beforeComposite": 0.1411764705882353,
      "afterComposite": 0.16470588235294117,
      "marginalDelta": 0.023529411764705882,
      "latencyMs": 139.054402,
      "components": {
        "exactRetrieval": 0,
        "staleMemoryRejection": 0,
        "temporalUpdateCorrectness": 0,
        "compressionSurvival": 0.5490196078431373,
        "routingAccuracy": 0,
        "latencyMs": 0
      },
      "parentStateRoot": "0xb914b4b8a89561c3f98471b55782bb05179dcd1ef4ad8bcd3edbfd21e490b795",
      "patchHashHex": "0x768029f732b4364b9cb39039d790488d2a9ee7a830297f7b356aae43ad345790"
    },
    {
      "epoch": 8,
      "accepted": true,
      "errorCode": null,
      "beforeComposite": 0.16470588235294117,
      "afterComposite": 0.18823529411764706,
      "marginalDelta": 0.023529411764705882,
      "latencyMs": 136.307442,
      "components": {
        "exactRetrieval": 0,
        "staleMemoryRejection": 0,
        "temporalUpdateCorrectness": 0,
        "compressionSurvival": 0.6274509803921569,
        "routingAccuracy": 0,
        "latencyMs": 0
      },
      "parentStateRoot": "0x242124f9a7034e44798475239cdb6a644d4dfe707329747e5747ed840e45c42e",
      "patchHashHex": "0x7d09870b630889b3d9b1034525418170024d08ebf809fafcaff39ee47c80fb1d"
    },
    {
      "epoch": 9,
      "accepted": true,
      "errorCode": null,
      "beforeComposite": 0.18823529411764706,
      "afterComposite": 0.21176470588235294,
      "marginalDelta": 0.023529411764705882,
      "latencyMs": 131.906879,
      "components": {
        "exactRetrieval": 0,
        "staleMemoryRejection": 0,
        "temporalUpdateCorrectness": 0,
        "compressionSurvival": 0.7058823529411765,
        "routingAccuracy": 0,
        "latencyMs": 0
      },
      "parentStateRoot": "0x0efd18557d006fda24373936750b0440f216e3d32cffff9d3e5343a3aeb1f0a3",
      "patchHashHex": "0x162622bda5eaa9eb5ebfdde67d4504e022648c3745313bd1c05b9d883c625841"
    },
    {
      "epoch": 10,
      "accepted": true,
      "errorCode": null,
      "beforeComposite": 0.21176470588235294,
      "afterComposite": 0.23529411764705882,
      "marginalDelta": 0.023529411764705882,
      "latencyMs": 134.016521,
      "components": {
        "exactRetrieval": 0,
        "staleMemoryRejection": 0,
        "temporalUpdateCorrectness": 0,
        "compressionSurvival": 0.7843137254901961,
        "routingAccuracy": 0,
        "latencyMs": 0
      },
      "parentStateRoot": "0x2ac8d3fe491c9bd3c97fdb9409ac032b3b87f824b08f1b037e5e1ede641e330b",
      "patchHashHex": "0x29311509db7a89742901fe9c25a7c268d2af8da20a88b3bf97095ecd09cad788"
    },
    {
      "epoch": 11,
      "accepted": true,
      "errorCode": null,
      "beforeComposite": 0.23529411764705882,
      "afterComposite": 0.25882352941176473,
      "marginalDelta": 0.02352941176470591,
      "latencyMs": 132.476442,
      "components": {
        "exactRetrieval": 0,
        "staleMemoryRejection": 0,
        "temporalUpdateCorrectness": 0,
        "compressionSurvival": 0.8627450980392157,
        "routingAccuracy": 0,
        "latencyMs": 0
      },
      "parentStateRoot": "0x583256b19c0f91a3777a091098a617372e6b5400fe815edec13191364099ae51",
      "patchHashHex": "0x61d263a41b1dcfdf7c4f1976394042c267abe2bf76a8af5a16f7f21459549bba"
    },
    {
      "epoch": 12,
      "accepted": false,
      "errorCode": "no_patch",
      "beforeComposite": 0.25882352941176473,
      "afterComposite": 0.25882352941176473,
      "marginalDelta": 0,
      "latencyMs": 0.032695,
      "components": {
        "exactRetrieval": 0,
        "staleMemoryRejection": 0,
        "temporalUpdateCorrectness": 0,
        "compressionSurvival": 0.8627450980392157,
        "routingAccuracy": 0,
        "latencyMs": 0
      },
      "parentStateRoot": "0x583256b19c0f91a3777a091098a617372e6b5400fe815edec13191364099ae51",
      "patchHashHex": null
    },
    {
      "epoch": 13,
      "accepted": false,
      "errorCode": "no_patch",
      "beforeComposite": 0.25882352941176473,
      "afterComposite": 0.25882352941176473,
      "marginalDelta": 0,
      "latencyMs": 0.037412,
      "components": {
        "exactRetrieval": 0,
        "staleMemoryRejection": 0,
        "temporalUpdateCorrectness": 0,
        "compressionSurvival": 0.8627450980392157,
        "routingAccuracy": 0,
        "latencyMs": 0
      },
      "parentStateRoot": "0x583256b19c0f91a3777a091098a617372e6b5400fe815edec13191364099ae51",
      "patchHashHex": null
    },
    {
      "epoch": 14,
      "accepted": false,
      "errorCode": "no_patch",
      "beforeComposite": 0.25882352941176473,
      "afterComposite": 0.25882352941176473,
      "marginalDelta": 0,
      "latencyMs": 0.038202,
      "components": {
        "exactRetrieval": 0,
        "staleMemoryRejection": 0,
        "temporalUpdateCorrectness": 0,
        "compressionSurvival": 0.8627450980392157,
        "routingAccuracy": 0,
        "latencyMs": 0
      },
      "parentStateRoot": "0x583256b19c0f91a3777a091098a617372e6b5400fe815edec13191364099ae51",
      "patchHashHex": null
    },
    {
      "epoch": 15,
      "accepted": false,
      "errorCode": "no_patch",
      "beforeComposite": 0.25882352941176473,
      "afterComposite": 0.25882352941176473,
      "marginalDelta": 0,
      "latencyMs": 0.045273,
      "components": {
        "exactRetrieval": 0,
        "staleMemoryRejection": 0,
        "temporalUpdateCorrectness": 0,
        "compressionSurvival": 0.8627450980392157,
        "routingAccuracy": 0,
        "latencyMs": 0
      },
      "parentStateRoot": "0x583256b19c0f91a3777a091098a617372e6b5400fe815edec13191364099ae51",
      "patchHashHex": null
    },
    {
      "epoch": 16,
      "accepted": false,
      "errorCode": "no_patch",
      "beforeComposite": 0.25882352941176473,
      "afterComposite": 0.25882352941176473,
      "marginalDelta": 0,
      "latencyMs": 0.038362,
      "components": {
        "exactRetrieval": 0,
        "staleMemoryRejection": 0,
        "temporalUpdateCorrectness": 0,
        "compressionSurvival": 0.8627450980392157,
        "routingAccuracy": 0,
        "latencyMs": 0
      },
      "parentStateRoot": "0x583256b19c0f91a3777a091098a617372e6b5400fe815edec13191364099ae51",
      "patchHashHex": null
    },
    {
      "epoch": 17,
      "accepted": false,
      "errorCode": "no_patch",
      "beforeComposite": 0.25882352941176473,
      "afterComposite": 0.25882352941176473,
      "marginalDelta": 0,
      "latencyMs": 0.033296,
      "components": {
        "exactRetrieval": 0,
        "staleMemoryRejection": 0,
        "temporalUpdateCorrectness": 0,
        "compressionSurvival": 0.8627450980392157,
        "routingAccuracy": 0,
        "latencyMs": 0
      },
      "parentStateRoot": "0x583256b19c0f91a3777a091098a617372e6b5400fe815edec13191364099ae51",
      "patchHashHex": null
    },
    {
      "epoch": 18,
      "accepted": false,
      "errorCode": "no_patch",
      "beforeComposite": 0.25882352941176473,
      "afterComposite": 0.25882352941176473,
      "marginalDelta": 0,
      "latencyMs": 0.03709,
      "components": {
        "exactRetrieval": 0,
        "staleMemoryRejection": 0,
        "temporalUpdateCorrectness": 0,
        "compressionSurvival": 0.8627450980392157,
        "routingAccuracy": 0,
        "latencyMs": 0
      },
      "parentStateRoot": "0x583256b19c0f91a3777a091098a617372e6b5400fe815edec13191364099ae51",
      "patchHashHex": null
    },
    {
      "epoch": 19,
      "accepted": false,
      "errorCode": "no_patch",
      "beforeComposite": 0.25882352941176473,
      "afterComposite": 0.25882352941176473,
      "marginalDelta": 0,
      "latencyMs": 0.046433,
      "components": {
        "exactRetrieval": 0,
        "staleMemoryRejection": 0,
        "temporalUpdateCorrectness": 0,
        "compressionSurvival": 0.8627450980392157,
        "routingAccuracy": 0,
        "latencyMs": 0
      },
      "parentStateRoot": "0x583256b19c0f91a3777a091098a617372e6b5400fe815edec13191364099ae51",
      "patchHashHex": null
    },
    {
      "epoch": 20,
      "accepted": false,
      "errorCode": "no_patch",
      "beforeComposite": 0.25882352941176473,
      "afterComposite": 0.25882352941176473,
      "marginalDelta": 0,
      "latencyMs": 0.038252,
      "components": {
        "exactRetrieval": 0,
        "staleMemoryRejection": 0,
        "temporalUpdateCorrectness": 0,
        "compressionSurvival": 0.8627450980392157,
        "routingAccuracy": 0,
        "latencyMs": 0
      },
      "parentStateRoot": "0x583256b19c0f91a3777a091098a617372e6b5400fe815edec13191364099ae51",
      "patchHashHex": null
    },
    {
      "epoch": 21,
      "accepted": false,
      "errorCode": "no_patch",
      "beforeComposite": 0.25882352941176473,
      "afterComposite": 0.25882352941176473,
      "marginalDelta": 0,
      "latencyMs": 0.038895,
      "components": {
        "exactRetrieval": 0,
        "staleMemoryRejection": 0,
        "temporalUpdateCorrectness": 0,
        "compressionSurvival": 0.8627450980392157,
        "routingAccuracy": 0,
        "latencyMs": 0
      },
      "parentStateRoot": "0x583256b19c0f91a3777a091098a617372e6b5400fe815edec13191364099ae51",
      "patchHashHex": null
    },
    {
      "epoch": 22,
      "accepted": false,
      "errorCode": "no_patch",
      "beforeComposite": 0.25882352941176473,
      "afterComposite": 0.25882352941176473,
      "marginalDelta": 0,
      "latencyMs": 0.038873,
      "components": {
        "exactRetrieval": 0,
        "staleMemoryRejection": 0,
        "temporalUpdateCorrectness": 0,
        "compressionSurvival": 0.8627450980392157,
        "routingAccuracy": 0,
        "latencyMs": 0
      },
      "parentStateRoot": "0x583256b19c0f91a3777a091098a617372e6b5400fe815edec13191364099ae51",
      "patchHashHex": null
    },
    {
      "epoch": 23,
      "accepted": false,
      "errorCode": "no_patch",
      "beforeComposite": 0.25882352941176473,
      "afterComposite": 0.25882352941176473,
      "marginalDelta": 0,
      "latencyMs": 0.037952,
      "components": {
        "exactRetrieval": 0,
        "staleMemoryRejection": 0,
        "temporalUpdateCorrectness": 0,
        "compressionSurvival": 0.8627450980392157,
        "routingAccuracy": 0,
        "latencyMs": 0
      },
      "parentStateRoot": "0x583256b19c0f91a3777a091098a617372e6b5400fe815edec13191364099ae51",
      "patchHashHex": null
    },
    {
      "epoch": 24,
      "accepted": false,
      "errorCode": "no_patch",
      "beforeComposite": 0.25882352941176473,
      "afterComposite": 0.25882352941176473,
      "marginalDelta": 0,
      "latencyMs": 0.039053,
      "components": {
        "exactRetrieval": 0,
        "staleMemoryRejection": 0,
        "temporalUpdateCorrectness": 0,
        "compressionSurvival": 0.8627450980392157,
        "routingAccuracy": 0,
        "latencyMs": 0
      },
      "parentStateRoot": "0x583256b19c0f91a3777a091098a617372e6b5400fe815edec13191364099ae51",
      "patchHashHex": null
    },
    {
      "epoch": 25,
      "accepted": false,
      "errorCode": "no_patch",
      "beforeComposite": 0.25882352941176473,
      "afterComposite": 0.25882352941176473,
      "marginalDelta": 0,
      "latencyMs": 0.036912,
      "components": {
        "exactRetrieval": 0,
        "staleMemoryRejection": 0,
        "temporalUpdateCorrectness": 0,
        "compressionSurvival": 0.8627450980392157,
        "routingAccuracy": 0,
        "latencyMs": 0
      },
      "parentStateRoot": "0x583256b19c0f91a3777a091098a617372e6b5400fe815edec13191364099ae51",
      "patchHashHex": null
    },
    {
      "epoch": 26,
      "accepted": false,
      "errorCode": "no_patch",
      "beforeComposite": 0.25882352941176473,
      "afterComposite": 0.25882352941176473,
      "marginalDelta": 0,
      "latencyMs": 0.03659,
      "components": {
        "exactRetrieval": 0,
        "staleMemoryRejection": 0,
        "temporalUpdateCorrectness": 0,
        "compressionSurvival": 0.8627450980392157,
        "routingAccuracy": 0,
        "latencyMs": 0
      },
      "parentStateRoot": "0x583256b19c0f91a3777a091098a617372e6b5400fe815edec13191364099ae51",
      "patchHashHex": null
    },
    {
      "epoch": 27,
      "accepted": false,
      "errorCode": "no_patch",
      "beforeComposite": 0.25882352941176473,
      "afterComposite": 0.25882352941176473,
      "marginalDelta": 0,
      "latencyMs": 0.037301,
      "components": {
        "exactRetrieval": 0,
        "staleMemoryRejection": 0,
        "temporalUpdateCorrectness": 0,
        "compressionSurvival": 0.8627450980392157,
        "routingAccuracy": 0,
        "latencyMs": 0
      },
      "parentStateRoot": "0x583256b19c0f91a3777a091098a617372e6b5400fe815edec13191364099ae51",
      "patchHashHex": null
    },
    {
      "epoch": 28,
      "accepted": false,
      "errorCode": "no_patch",
      "beforeComposite": 0.25882352941176473,
      "afterComposite": 0.25882352941176473,
      "marginalDelta": 0,
      "latencyMs": 0.031513,
      "components": {
        "exactRetrieval": 0,
        "staleMemoryRejection": 0,
        "temporalUpdateCorrectness": 0,
        "compressionSurvival": 0.8627450980392157,
        "routingAccuracy": 0,
        "latencyMs": 0
      },
      "parentStateRoot": "0x583256b19c0f91a3777a091098a617372e6b5400fe815edec13191364099ae51",
      "patchHashHex": null
    },
    {
      "epoch": 29,
      "accepted": false,
      "errorCode": "no_patch",
      "beforeComposite": 0.25882352941176473,
      "afterComposite": 0.25882352941176473,
      "marginalDelta": 0,
      "latencyMs": 0.045442,
      "components": {
        "exactRetrieval": 0,
        "staleMemoryRejection": 0,
        "temporalUpdateCorrectness": 0,
        "compressionSurvival": 0.8627450980392157,
        "routingAccuracy": 0,
        "latencyMs": 0
      },
      "parentStateRoot": "0x583256b19c0f91a3777a091098a617372e6b5400fe815edec13191364099ae51",
      "patchHashHex": null
    },
    {
      "epoch": 30,
      "accepted": false,
      "errorCode": "no_patch",
      "beforeComposite": 0.25882352941176473,
      "afterComposite": 0.25882352941176473,
      "marginalDelta": 0,
      "latencyMs": 0.036731,
      "components": {
        "exactRetrieval": 0,
        "staleMemoryRejection": 0,
        "temporalUpdateCorrectness": 0,
        "compressionSurvival": 0.8627450980392157,
        "routingAccuracy": 0,
        "latencyMs": 0
      },
      "parentStateRoot": "0x583256b19c0f91a3777a091098a617372e6b5400fe815edec13191364099ae51",
      "patchHashHex": null
    },
    {
      "epoch": 31,
      "accepted": false,
      "errorCode": "no_patch",
      "beforeComposite": 0.25882352941176473,
      "afterComposite": 0.25882352941176473,
      "marginalDelta": 0,
      "latencyMs": 0.038472,
      "components": {
        "exactRetrieval": 0,
        "staleMemoryRejection": 0,
        "temporalUpdateCorrectness": 0,
        "compressionSurvival": 0.8627450980392157,
        "routingAccuracy": 0,
        "latencyMs": 0
      },
      "parentStateRoot": "0x583256b19c0f91a3777a091098a617372e6b5400fe815edec13191364099ae51",
      "patchHashHex": null
    },
    {
      "epoch": 32,
      "accepted": false,
      "errorCode": "no_patch",
      "beforeComposite": 0.25882352941176473,
      "afterComposite": 0.25882352941176473,
      "marginalDelta": 0,
      "latencyMs": 0.038984,
      "components": {
        "exactRetrieval": 0,
        "staleMemoryRejection": 0,
        "temporalUpdateCorrectness": 0,
        "compressionSurvival": 0.8627450980392157,
        "routingAccuracy": 0,
        "latencyMs": 0
      },
      "parentStateRoot": "0x583256b19c0f91a3777a091098a617372e6b5400fe815edec13191364099ae51",
      "patchHashHex": null
    },
    {
      "epoch": 33,
      "accepted": false,
      "errorCode": "no_patch",
      "beforeComposite": 0.25882352941176473,
      "afterComposite": 0.25882352941176473,
      "marginalDelta": 0,
      "latencyMs": 0.033667,
      "components": {
        "exactRetrieval": 0,
        "staleMemoryRejection": 0,
        "temporalUpdateCorrectness": 0,
        "compressionSurvival": 0.8627450980392157,
        "routingAccuracy": 0,
        "latencyMs": 0
      },
      "parentStateRoot": "0x583256b19c0f91a3777a091098a617372e6b5400fe815edec13191364099ae51",
      "patchHashHex": null
    },
    {
      "epoch": 34,
      "accepted": false,
      "errorCode": "no_patch",
      "beforeComposite": 0.25882352941176473,
      "afterComposite": 0.25882352941176473,
      "marginalDelta": 0,
      "latencyMs": 0.037141,
      "components": {
        "exactRetrieval": 0,
        "staleMemoryRejection": 0,
        "temporalUpdateCorrectness": 0,
        "compressionSurvival": 0.8627450980392157,
        "routingAccuracy": 0,
        "latencyMs": 0
      },
      "parentStateRoot": "0x583256b19c0f91a3777a091098a617372e6b5400fe815edec13191364099ae51",
      "patchHashHex": null
    },
    {
      "epoch": 35,
      "accepted": false,
      "errorCode": "no_patch",
      "beforeComposite": 0.25882352941176473,
      "afterComposite": 0.25882352941176473,
      "marginalDelta": 0,
      "latencyMs": 0.038842,
      "components": {
        "exactRetrieval": 0,
        "staleMemoryRejection": 0,
        "temporalUpdateCorrectness": 0,
        "compressionSurvival": 0.8627450980392157,
        "routingAccuracy": 0,
        "latencyMs": 0
      },
      "parentStateRoot": "0x583256b19c0f91a3777a091098a617372e6b5400fe815edec13191364099ae51",
      "patchHashHex": null
    },
    {
      "epoch": 36,
      "accepted": false,
      "errorCode": "no_patch",
      "beforeComposite": 0.25882352941176473,
      "afterComposite": 0.25882352941176473,
      "marginalDelta": 0,
      "latencyMs": 0.038353,
      "components": {
        "exactRetrieval": 0,
        "staleMemoryRejection": 0,
        "temporalUpdateCorrectness": 0,
        "compressionSurvival": 0.8627450980392157,
        "routingAccuracy": 0,
        "latencyMs": 0
      },
      "parentStateRoot": "0x583256b19c0f91a3777a091098a617372e6b5400fe815edec13191364099ae51",
      "patchHashHex": null
    },
    {
      "epoch": 37,
      "accepted": false,
      "errorCode": "no_patch",
      "beforeComposite": 0.25882352941176473,
      "afterComposite": 0.25882352941176473,
      "marginalDelta": 0,
      "latencyMs": 0.0358,
      "components": {
        "exactRetrieval": 0,
        "staleMemoryRejection": 0,
        "temporalUpdateCorrectness": 0,
        "compressionSurvival": 0.8627450980392157,
        "routingAccuracy": 0,
        "latencyMs": 0
      },
      "parentStateRoot": "0x583256b19c0f91a3777a091098a617372e6b5400fe815edec13191364099ae51",
      "patchHashHex": null
    },
    {
      "epoch": 38,
      "accepted": false,
      "errorCode": "no_patch",
      "beforeComposite": 0.25882352941176473,
      "afterComposite": 0.25882352941176473,
      "marginalDelta": 0,
      "latencyMs": 0.031934,
      "components": {
        "exactRetrieval": 0,
        "staleMemoryRejection": 0,
        "temporalUpdateCorrectness": 0,
        "compressionSurvival": 0.8627450980392157,
        "routingAccuracy": 0,
        "latencyMs": 0
      },
      "parentStateRoot": "0x583256b19c0f91a3777a091098a617372e6b5400fe815edec13191364099ae51",
      "patchHashHex": null
    },
    {
      "epoch": 39,
      "accepted": false,
      "errorCode": "no_patch",
      "beforeComposite": 0.25882352941176473,
      "afterComposite": 0.25882352941176473,
      "marginalDelta": 0,
      "latencyMs": 0.032625,
      "components": {
        "exactRetrieval": 0,
        "staleMemoryRejection": 0,
        "temporalUpdateCorrectness": 0,
        "compressionSurvival": 0.8627450980392157,
        "routingAccuracy": 0,
        "latencyMs": 0
      },
      "parentStateRoot": "0x583256b19c0f91a3777a091098a617372e6b5400fe815edec13191364099ae51",
      "patchHashHex": null
    },
    {
      "epoch": 40,
      "accepted": false,
      "errorCode": "no_patch",
      "beforeComposite": 0.25882352941176473,
      "afterComposite": 0.25882352941176473,
      "marginalDelta": 0,
      "latencyMs": 0.035349,
      "components": {
        "exactRetrieval": 0,
        "staleMemoryRejection": 0,
        "temporalUpdateCorrectness": 0,
        "compressionSurvival": 0.8627450980392157,
        "routingAccuracy": 0,
        "latencyMs": 0
      },
      "parentStateRoot": "0x583256b19c0f91a3777a091098a617372e6b5400fe815edec13191364099ae51",
      "patchHashHex": null
    },
    {
      "epoch": 41,
      "accepted": false,
      "errorCode": "no_patch",
      "beforeComposite": 0.25882352941176473,
      "afterComposite": 0.25882352941176473,
      "marginalDelta": 0,
      "latencyMs": 0.023683,
      "components": {
        "exactRetrieval": 0,
        "staleMemoryRejection": 0,
        "temporalUpdateCorrectness": 0,
        "compressionSurvival": 0.8627450980392157,
        "routingAccuracy": 0,
        "latencyMs": 0
      },
      "parentStateRoot": "0x583256b19c0f91a3777a091098a617372e6b5400fe815edec13191364099ae51",
      "patchHashHex": null
    },
    {
      "epoch": 42,
      "accepted": false,
      "errorCode": "no_patch",
      "beforeComposite": 0.25882352941176473,
      "afterComposite": 0.25882352941176473,
      "marginalDelta": 0,
      "latencyMs": 0.022811,
      "components": {
        "exactRetrieval": 0,
        "staleMemoryRejection": 0,
        "temporalUpdateCorrectness": 0,
        "compressionSurvival": 0.8627450980392157,
        "routingAccuracy": 0,
        "latencyMs": 0
      },
      "parentStateRoot": "0x583256b19c0f91a3777a091098a617372e6b5400fe815edec13191364099ae51",
      "patchHashHex": null
    },
    {
      "epoch": 43,
      "accepted": false,
      "errorCode": "no_patch",
      "beforeComposite": 0.25882352941176473,
      "afterComposite": 0.25882352941176473,
      "marginalDelta": 0,
      "latencyMs": 0.022191,
      "components": {
        "exactRetrieval": 0,
        "staleMemoryRejection": 0,
        "temporalUpdateCorrectness": 0,
        "compressionSurvival": 0.8627450980392157,
        "routingAccuracy": 0,
        "latencyMs": 0
      },
      "parentStateRoot": "0x583256b19c0f91a3777a091098a617372e6b5400fe815edec13191364099ae51",
      "patchHashHex": null
    },
    {
      "epoch": 44,
      "accepted": false,
      "errorCode": "no_patch",
      "beforeComposite": 0.25882352941176473,
      "afterComposite": 0.25882352941176473,
      "marginalDelta": 0,
      "latencyMs": 0.019928,
      "components": {
        "exactRetrieval": 0,
        "staleMemoryRejection": 0,
        "temporalUpdateCorrectness": 0,
        "compressionSurvival": 0.8627450980392157,
        "routingAccuracy": 0,
        "latencyMs": 0
      },
      "parentStateRoot": "0x583256b19c0f91a3777a091098a617372e6b5400fe815edec13191364099ae51",
      "patchHashHex": null
    },
    {
      "epoch": 45,
      "accepted": false,
      "errorCode": "no_patch",
      "beforeComposite": 0.25882352941176473,
      "afterComposite": 0.25882352941176473,
      "marginalDelta": 0,
      "latencyMs": 0.02167,
      "components": {
        "exactRetrieval": 0,
        "staleMemoryRejection": 0,
        "temporalUpdateCorrectness": 0,
        "compressionSurvival": 0.8627450980392157,
        "routingAccuracy": 0,
        "latencyMs": 0
      },
      "parentStateRoot": "0x583256b19c0f91a3777a091098a617372e6b5400fe815edec13191364099ae51",
      "patchHashHex": null
    },
    {
      "epoch": 46,
      "accepted": false,
      "errorCode": "no_patch",
      "beforeComposite": 0.25882352941176473,
      "afterComposite": 0.25882352941176473,
      "marginalDelta": 0,
      "latencyMs": 0.02176,
      "components": {
        "exactRetrieval": 0,
        "staleMemoryRejection": 0,
        "temporalUpdateCorrectness": 0,
        "compressionSurvival": 0.8627450980392157,
        "routingAccuracy": 0,
        "latencyMs": 0
      },
      "parentStateRoot": "0x583256b19c0f91a3777a091098a617372e6b5400fe815edec13191364099ae51",
      "patchHashHex": null
    },
    {
      "epoch": 47,
      "accepted": false,
      "errorCode": "no_patch",
      "beforeComposite": 0.25882352941176473,
      "afterComposite": 0.25882352941176473,
      "marginalDelta": 0,
      "latencyMs": 0.023513,
      "components": {
        "exactRetrieval": 0,
        "staleMemoryRejection": 0,
        "temporalUpdateCorrectness": 0,
        "compressionSurvival": 0.8627450980392157,
        "routingAccuracy": 0,
        "latencyMs": 0
      },
      "parentStateRoot": "0x583256b19c0f91a3777a091098a617372e6b5400fe815edec13191364099ae51",
      "patchHashHex": null
    },
    {
      "epoch": 48,
      "accepted": false,
      "errorCode": "no_patch",
      "beforeComposite": 0.25882352941176473,
      "afterComposite": 0.25882352941176473,
      "marginalDelta": 0,
      "latencyMs": 0.029661,
      "components": {
        "exactRetrieval": 0,
        "staleMemoryRejection": 0,
        "temporalUpdateCorrectness": 0,
        "compressionSurvival": 0.8627450980392157,
        "routingAccuracy": 0,
        "latencyMs": 0
      },
      "parentStateRoot": "0x583256b19c0f91a3777a091098a617372e6b5400fe815edec13191364099ae51",
      "patchHashHex": null
    },
    {
      "epoch": 49,
      "accepted": false,
      "errorCode": "no_patch",
      "beforeComposite": 0.25882352941176473,
      "afterComposite": 0.25882352941176473,
      "marginalDelta": 0,
      "latencyMs": 0.024254,
      "components": {
        "exactRetrieval": 0,
        "staleMemoryRejection": 0,
        "temporalUpdateCorrectness": 0,
        "compressionSurvival": 0.8627450980392157,
        "routingAccuracy": 0,
        "latencyMs": 0
      },
      "parentStateRoot": "0x583256b19c0f91a3777a091098a617372e6b5400fe815edec13191364099ae51",
      "patchHashHex": null
    },
    {
      "epoch": 50,
      "accepted": false,
      "errorCode": "no_patch",
      "beforeComposite": 0.25882352941176473,
      "afterComposite": 0.25882352941176473,
      "marginalDelta": 0,
      "latencyMs": 0.020919,
      "components": {
        "exactRetrieval": 0,
        "staleMemoryRejection": 0,
        "temporalUpdateCorrectness": 0,
        "compressionSurvival": 0.8627450980392157,
        "routingAccuracy": 0,
        "latencyMs": 0
      },
      "parentStateRoot": "0x583256b19c0f91a3777a091098a617372e6b5400fe815edec13191364099ae51",
      "patchHashHex": null
    },
    {
      "epoch": 51,
      "accepted": false,
      "errorCode": "no_patch",
      "beforeComposite": 0.25882352941176473,
      "afterComposite": 0.25882352941176473,
      "marginalDelta": 0,
      "latencyMs": 0.028279,
      "components": {
        "exactRetrieval": 0,
        "staleMemoryRejection": 0,
        "temporalUpdateCorrectness": 0,
        "compressionSurvival": 0.8627450980392157,
        "routingAccuracy": 0,
        "latencyMs": 0
      },
      "parentStateRoot": "0x583256b19c0f91a3777a091098a617372e6b5400fe815edec13191364099ae51",
      "patchHashHex": null
    },
    {
      "epoch": 52,
      "accepted": false,
      "errorCode": "no_patch",
      "beforeComposite": 0.25882352941176473,
      "afterComposite": 0.25882352941176473,
      "marginalDelta": 0,
      "latencyMs": 0.024173,
      "components": {
        "exactRetrieval": 0,
        "staleMemoryRejection": 0,
        "temporalUpdateCorrectness": 0,
        "compressionSurvival": 0.8627450980392157,
        "routingAccuracy": 0,
        "latencyMs": 0
      },
      "parentStateRoot": "0x583256b19c0f91a3777a091098a617372e6b5400fe815edec13191364099ae51",
      "patchHashHex": null
    },
    {
      "epoch": 53,
      "accepted": false,
      "errorCode": "no_patch",
      "beforeComposite": 0.25882352941176473,
      "afterComposite": 0.25882352941176473,
      "marginalDelta": 0,
      "latencyMs": 0.020619,
      "components": {
        "exactRetrieval": 0,
        "staleMemoryRejection": 0,
        "temporalUpdateCorrectness": 0,
        "compressionSurvival": 0.8627450980392157,
        "routingAccuracy": 0,
        "latencyMs": 0
      },
      "parentStateRoot": "0x583256b19c0f91a3777a091098a617372e6b5400fe815edec13191364099ae51",
      "patchHashHex": null
    },
    {
      "epoch": 54,
      "accepted": false,
      "errorCode": "no_patch",
      "beforeComposite": 0.25882352941176473,
      "afterComposite": 0.25882352941176473,
      "marginalDelta": 0,
      "latencyMs": 0.027268,
      "components": {
        "exactRetrieval": 0,
        "staleMemoryRejection": 0,
        "temporalUpdateCorrectness": 0,
        "compressionSurvival": 0.8627450980392157,
        "routingAccuracy": 0,
        "latencyMs": 0
      },
      "parentStateRoot": "0x583256b19c0f91a3777a091098a617372e6b5400fe815edec13191364099ae51",
      "patchHashHex": null
    },
    {
      "epoch": 55,
      "accepted": false,
      "errorCode": "no_patch",
      "beforeComposite": 0.25882352941176473,
      "afterComposite": 0.25882352941176473,
      "marginalDelta": 0,
      "latencyMs": 0.020759,
      "components": {
        "exactRetrieval": 0,
        "staleMemoryRejection": 0,
        "temporalUpdateCorrectness": 0,
        "compressionSurvival": 0.8627450980392157,
        "routingAccuracy": 0,
        "latencyMs": 0
      },
      "parentStateRoot": "0x583256b19c0f91a3777a091098a617372e6b5400fe815edec13191364099ae51",
      "patchHashHex": null
    },
    {
      "epoch": 56,
      "accepted": false,
      "errorCode": "no_patch",
      "beforeComposite": 0.25882352941176473,
      "afterComposite": 0.25882352941176473,
      "marginalDelta": 0,
      "latencyMs": 0.024163,
      "components": {
        "exactRetrieval": 0,
        "staleMemoryRejection": 0,
        "temporalUpdateCorrectness": 0,
        "compressionSurvival": 0.8627450980392157,
        "routingAccuracy": 0,
        "latencyMs": 0
      },
      "parentStateRoot": "0x583256b19c0f91a3777a091098a617372e6b5400fe815edec13191364099ae51",
      "patchHashHex": null
    },
    {
      "epoch": 57,
      "accepted": false,
      "errorCode": "no_patch",
      "beforeComposite": 0.25882352941176473,
      "afterComposite": 0.25882352941176473,
      "marginalDelta": 0,
      "latencyMs": 0.022231,
      "components": {
        "exactRetrieval": 0,
        "staleMemoryRejection": 0,
        "temporalUpdateCorrectness": 0,
        "compressionSurvival": 0.8627450980392157,
        "routingAccuracy": 0,
        "latencyMs": 0
      },
      "parentStateRoot": "0x583256b19c0f91a3777a091098a617372e6b5400fe815edec13191364099ae51",
      "patchHashHex": null
    },
    {
      "epoch": 58,
      "accepted": false,
      "errorCode": "no_patch",
      "beforeComposite": 0.25882352941176473,
      "afterComposite": 0.25882352941176473,
      "marginalDelta": 0,
      "latencyMs": 0.022592,
      "components": {
        "exactRetrieval": 0,
        "staleMemoryRejection": 0,
        "temporalUpdateCorrectness": 0,
        "compressionSurvival": 0.8627450980392157,
        "routingAccuracy": 0,
        "latencyMs": 0
      },
      "parentStateRoot": "0x583256b19c0f91a3777a091098a617372e6b5400fe815edec13191364099ae51",
      "patchHashHex": null
    },
    {
      "epoch": 59,
      "accepted": false,
      "errorCode": "no_patch",
      "beforeComposite": 0.25882352941176473,
      "afterComposite": 0.25882352941176473,
      "marginalDelta": 0,
      "latencyMs": 0.020998,
      "components": {
        "exactRetrieval": 0,
        "staleMemoryRejection": 0,
        "temporalUpdateCorrectness": 0,
        "compressionSurvival": 0.8627450980392157,
        "routingAccuracy": 0,
        "latencyMs": 0
      },
      "parentStateRoot": "0x583256b19c0f91a3777a091098a617372e6b5400fe815edec13191364099ae51",
      "patchHashHex": null
    },
    {
      "epoch": 60,
      "accepted": false,
      "errorCode": "no_patch",
      "beforeComposite": 0.25882352941176473,
      "afterComposite": 0.25882352941176473,
      "marginalDelta": 0,
      "latencyMs": 0.023351,
      "components": {
        "exactRetrieval": 0,
        "staleMemoryRejection": 0,
        "temporalUpdateCorrectness": 0,
        "compressionSurvival": 0.8627450980392157,
        "routingAccuracy": 0,
        "latencyMs": 0
      },
      "parentStateRoot": "0x583256b19c0f91a3777a091098a617372e6b5400fe815edec13191364099ae51",
      "patchHashHex": null
    }
  ],
  "summary": {
    "totalEpochs": 60,
    "accepted": 11,
    "rejected": 49,
    "genesisComposite": 0,
    "finalComposite": 0.25882352941176473,
    "netImprovement": 0.25882352941176473,
    "avgScoreDelta": 0.004313725490196079,
    "p50LatencyMs": 0.036912,
    "p99LatencyMs": 139.054402,
    "finalStateRoot": "0x583256b19c0f91a3777a091098a617372e6b5400fe815edec13191364099ae51",
    "genesisStateRoot": "0x7e704f76d6156405800141206cec1e6d7804daa8bf4e7da1542a1e431958504e",
    "familyContribution": {
      "near_collision": 0,
      "temporal": 0,
      "long_horizon": 0.8627450980392157,
      "routing": 0,
      "exact": 0,
      "stale": 0,
      "current": 0
    },
    "finalComponents": {
      "exactRetrieval": 0,
      "staleMemoryRejection": 0,
      "temporalUpdateCorrectness": 0,
      "compressionSurvival": 0.8627450980392157,
      "routingAccuracy": 0,
      "latencyMs": 0
    },
    "finalFamilyScores": {
      "near_collision": 0,
      "temporal": 0,
      "long_horizon": 0.7394957983193279
    },
    "finalHits": {
      "near_collision": 0,
      "stale": 0,
      "current": 0,
      "long_horizon": 44,
      "relations": 0
    },
    "finalTotals": {
      "near_collision": 51,
      "stale": 55,
      "current": 57,
      "long_horizon": 51,
      "relations": 128
    }
  },
  "generatedAt": "2026-05-06T09:34:38.371Z",
  "corpusSources": {
    "near_collision": {
      "path": "benchmark/fixtures/near_collision/limit_nq_hotpotqa_v0.json",
      "count": 51,
      "license": "CC-BY-4.0 (LIMIT); Apache-2.0 (NQ); CC-BY-SA-4.0 (HotpotQA)",
      "source": [
        "LIMIT",
        "BEIR_NQ",
        "BEIR_HotpotQA"
      ]
    },
    "temporal": {
      "path": "benchmark/fixtures/temporal/memoryagentbench_v0.json",
      "count": 52,
      "license": "MIT",
      "source": "MemoryAgentBench"
    },
    "long_horizon": {
      "path": "benchmark/fixtures/long_horizon/memoryarena_v0.json",
      "count": 51,
      "license": "CC-BY-4.0",
      "source": "MemoryArena"
    },
    "synthetic_temporal": {
      "count": 60,
      "license": "Apache-2.0"
    }
  },
  "scoring": "real-cortexbench-v0"
}